pyiosbackup/__init__.py
pyiosbackup/__main__.py
pyiosbackup/backup.py
pyiosbackup/entry.py
pyiosbackup/exceptions.py
pyiosbackup/keybag.py
pyiosbackup/manifest_plist.py
pyiosbackup/manifest_dbs/__init__.py
pyiosbackup/manifest_dbs/factory.py
pyiosbackup/manifest_dbs/manifest_db_interface.py
pyiosbackup/manifest_dbs/mbdb.py
pyiosbackup/manifest_dbs/sqlite3.py
pyiosbackup-0.2.3.dist-info/LICENSE
pyiosbackup-0.2.3.dist-info/METADATA
pyiosbackup-0.2.3.dist-info/WHEEL
pyiosbackup-0.2.3.dist-info/entry_points.txt
pyiosbackup-0.2.3.dist-info/top_level.txt
pyiosbackup-0.2.3.dist-info/RECORD
