Metadata-Version: 2.1
Name: pyiosbackup
Version: 0.2.3
Summary: A python parser for iOS backups
Author-email: Matan Perelman <matan1008@gmail.com>
Maintainer-email: Matan Perelman <matan1008@gmail.com>
License: GNU GENERAL PUBLIC LICENSE
Project-URL: Homepage, https://github.com/matan1008/pyiosbackup
Project-URL: Bug Reports, https://github.com/matan1008/pyiosbackup/issues
Keywords: ios,backup,automation
Classifier: Development Status :: 5 - Production/Stable
Classifier: License :: OSI Approved :: GNU General Public License v3 or later (GPLv3+)
Classifier: Programming Language :: Python :: 3
Classifier: Programming Language :: Python :: 3.7
Classifier: Programming Language :: Python :: 3.8
Classifier: Programming Language :: Python :: 3.9
Classifier: Programming Language :: Python :: 3.10
Classifier: Programming Language :: Python :: 3.11
Classifier: Programming Language :: Python :: 3 :: Only
Requires-Python: >=3.7
License-File: LICENSE
Requires-Dist: bpylist2 (>=4.0.1)
Requires-Dist: cryptography (>=35.0.0)
Requires-Dist: packaging
Requires-Dist: construct
Requires-Dist: click
Provides-Extra: test
Requires-Dist: pytest ; extra == 'test'
